nrf24/__init__.py
nrf24/nrf24.py
nrf24-2.0.0.dist-info/LICENSE
nrf24-2.0.0.dist-info/METADATA
nrf24-2.0.0.dist-info/WHEEL
nrf24-2.0.0.dist-info/top_level.txt
nrf24-2.0.0.dist-info/RECORD
