Metadata-Version: 2.1
Name: nrf24
Version: 2.0.0
Summary: A package enabling communication using NRF24L01 modules.
Home-page: https://github.com/bjarne-hansen/py-nrf24
Author: Bjarne Hansen
Author-email: bjarne@conspicio.dk
License: MIT
Keywords: nrf24l01 iot raspberry arduino
Platform: UNKNOWN
Classifier: Development Status :: 5 - Production/Stable
Classifier: Programming Language :: Python :: 3.6
Classifier: License :: OSI Approved :: MIT License
Classifier: Operating System :: OS Independent
Requires-Python: >=3.6
